{
    "pokemon": [
        {
            "num": 1,
            "name": "Bulbasaur",
            "health": 45,
            "attack": 12,
            "defense": 12,
            "speed": 8,
            "moves": [ 1, 2]
        },
        {
            "num": 2,
            "name": "Charmander",
            "health": 44,
            "attack": 14,
            "defense": 10,
            "speed": 12,
            "moves": [ 1, 3]
        },
        {
            "num": 3,
            "name": "Squirtle",
            "health": 50,
            "attack": 10,
            "defense": 15,
            "speed": 7,
            "moves": [ 1, 4]
        }
    ]
}